<annotation>
	<folder>HitMealDataset400x300</folder>
	<filename>126.jpg</filename>
	<path>D:\Programs\matlab\deep-learning\hitmeal\HitMealDataset400x300\126.jpg</path>
	<source>
		<database>Unknown</database>
	</source>
	<size>
		<width>400</width>
		<height>300</height>
		<depth>3</depth>
	</size>
	<segmented>0</segmented>
	<object>
		<name>rice</name>
		<pose>Unspecified</pose>
		<truncated>0</truncated>
		<difficult>0</difficult>
		<bndbox>
			<xmin>53</xmin>
			<ymin>154</ymin>
			<xmax>367</xmax>
			<ymax>279</ymax>
		</bndbox>
	</object>
	<object>
		<name>sqz</name>
		<pose>Unspecified</pose>
		<truncated>0</truncated>
		<difficult>0</difficult>
		<bndbox>
			<xmin>252</xmin>
			<ymin>37</ymin>
			<xmax>362</xmax>
			<ymax>163</ymax>
		</bndbox>
	</object>
</annotation>
