<annotation>
	<folder>HITSZMealDataset400x300</folder>
	<filename>133.jpg</filename>
	<path>C:/Users/Jingxuan.Yang/Documents/MATLAB/AIHomework/data/HITSZMealDataset400x300/133.jpg</path>
	<source>
		<database>Unknown</database>
	</source>
	<size>
		<width>400</width>
		<height>300</height>
		<depth>3</depth>
	</size>
	<segmented>0</segmented>
	<object>
		<name>szrp</name>
		<pose>Unspecified</pose>
		<truncated>0</truncated>
		<difficult>0</difficult>
		<bndbox>
			<xmin>101</xmin>
			<ymin>159</ymin>
			<xmax>216</xmax>
			<ymax>273</ymax>
		</bndbox>
	</object>
	<object>
		<name>r1</name>
		<pose>Unspecified</pose>
		<truncated>0</truncated>
		<difficult>0</difficult>
		<bndbox>
			<xmin>242</xmin>
			<ymin>162</ymin>
			<xmax>349</xmax>
			<ymax>255</ymax>
		</bndbox>
	</object>
</annotation>
