<annotation>
	<folder>HITSZMealDataset400x300</folder>
	<filename>231.jpg</filename>
	<path>C:/Users/Jingxuan.Yang/Documents/MATLAB/AIHomework/data/HITSZMealDataset400x300/231.jpg</path>
	<source>
		<database>Unknown</database>
	</source>
	<size>
		<width>400</width>
		<height>300</height>
		<depth>3</depth>
	</size>
	<segmented>0</segmented>
	<object>
		<name>yt</name>
		<pose>Unspecified</pose>
		<truncated>0</truncated>
		<difficult>0</difficult>
		<bndbox>
			<xmin>35</xmin>
			<ymin>37</ymin>
			<xmax>179</xmax>
			<ymax>266</ymax>
		</bndbox>
	</object>
	<object>
		<name>rice</name>
		<pose>Unspecified</pose>
		<truncated>0</truncated>
		<difficult>0</difficult>
		<bndbox>
			<xmin>213</xmin>
			<ymin>35</ymin>
			<xmax>366</xmax>
			<ymax>146</ymax>
		</bndbox>
	</object>
	<object>
		<name>r5</name>
		<pose>Unspecified</pose>
		<truncated>0</truncated>
		<difficult>0</difficult>
		<bndbox>
			<xmin>204</xmin>
			<ymin>157</ymin>
			<xmax>359</xmax>
			<ymax>281</ymax>
		</bndbox>
	</object>
</annotation>
