<annotation>
	<folder>HitMealDataset400x300</folder>
	<filename>5.jpg</filename>
	<path>D:\programs\matlab\ai2020\hitmeal\HitMealDataset400x300\5.jpg</path>
	<source>
		<database>Unknown</database>
	</source>
	<size>
		<width>400</width>
		<height>300</height>
		<depth>3</depth>
	</size>
	<segmented>0</segmented>
	<object>
		<name>gbr</name>
		<pose>Unspecified</pose>
		<truncated>0</truncated>
		<difficult>0</difficult>
		<bndbox>
			<xmin>62</xmin>
			<ymin>38</ymin>
			<xmax>203</xmax>
			<ymax>172</ymax>
		</bndbox>
	</object>
	<object>
		<name>ymc</name>
		<pose>Unspecified</pose>
		<truncated>0</truncated>
		<difficult>0</difficult>
		<bndbox>
			<xmin>47</xmin>
			<ymin>168</ymin>
			<xmax>212</xmax>
			<ymax>273</ymax>
		</bndbox>
	</object>
</annotation>
